LICENSE
README.md
setup.cfg
setup.py
pydownsongs/__init__.py
pydownsongs/__main__.py
pydownsongs/meta.py
pydownsongs/others.py
pydownsongs/songs.py
pydownsongs/spotlist.py
pydownsongs.egg-info/PKG-INFO
pydownsongs.egg-info/SOURCES.txt
pydownsongs.egg-info/dependency_links.txt
pydownsongs.egg-info/entry_points.txt
pydownsongs.egg-info/requires.txt
pydownsongs.egg-info/top_level.txt
pydownsongs/modules/__init__.py
pydownsongs/modules/y1_youtube-to-mp3_org.py
pydownsongs/modules/youtube_dl_module.py
pydownsongs/modules/yt5s_com.py