Metadata-Version: 2.1
Name: pydownsongs
Version: 1.6
Summary: Pydownsongs is intended for both developers and regular users to download songs
Home-page: https://github.com/hemish04082005/pydownsongs/
Author: Hemish
Author-email: hemish04082005@gmail.com
License: MIT
Download-URL: https://github.com/hemish04082005/pydownsongs/archive/1.6.tar.gz
Project-URL: Bug Tracker, https://github.com/hemish04082005/pydownsongs/issues
Keywords: python,downloader,download,songs,python3,youtube,youtube-dl
Platform: any
Classifier: Programming Language :: Python :: 3
Classifier: License :: OSI Approved :: MIT License
Classifier: Operating System :: OS Independent
Requires-Python: >=3.4
License-File: LICENSE
